pyroclient/__init__.py
pyroclient/client.py
pyroclient/exceptions.py
pyroclient/version.py
pyroclient-0.1.2.dist-info/LICENSE
pyroclient-0.1.2.dist-info/METADATA
pyroclient-0.1.2.dist-info/WHEEL
pyroclient-0.1.2.dist-info/top_level.txt
pyroclient-0.1.2.dist-info/zip-safe
pyroclient-0.1.2.dist-info/RECORD
